MyColorsPy/MyColorsPy.py
MyColorsPy/__init__.py
MyColorsPy-0.1.3.dist-info/METADATA
MyColorsPy-0.1.3.dist-info/WHEEL
MyColorsPy-0.1.3.dist-info/top_level.txt
MyColorsPy-0.1.3.dist-info/RECORD
