Metadata-Version: 2.1
Name: MyColorsPy
Version: 0.1.3
Summary: Module for using color in win command line or terminal.
Home-page: https://github.com/VolodyaHoi/MyColorsPy
Author: VolodyaHoi
Author-email: i4masyrov@gmail.com
